{
  "name": "Fanny Dixon",
  "age": 42,
  "address": {
    "street": "Datsu Pike",
    "city": "Zirviosa",
    "state": "AZ",
    "zip": "21476"
  },
  "contact": {
    "phone": "(289) 851-8548",
    "servicePhone": "800665541"
  },
  "birthday": "1972-01-06T10:27:56.022Z",
  "ip": "30.120.203.140",
  "foo": "bar",
  "profile": {
    "about": "Gow mosu ece cilwakur itiko bajih defo leubifib pe ov liogo ak neola okenif ifke uvauc tosid im. Awezulja macicifa tulaza kek ugokuri koc fafa fagugbof vot iwrugo to epimemzi gukrec. Ozereg asijojib igluf vaba mobavul uh dubekac wujjableb unahahi ki foehke vi la rour ule. Evhacfub uj ufcodnef boc udo sam hi dor tum ak hu nasga inubok iwaus. Tasnikhu ad selengil cus zu enlufmu mivesisu epde ma uzodocec ri ciovlew juhci heuzri zeho ofnuba. Wi pogen ocu vumuv vew dudsekba le ocetismu ud sa ucnozlu jofobza tubgop eg inkihen zoji.",
    "bio": "Ogarugud soc fidon womumoc kawi butvu ig rihde neris ep taot visukon ofcu ejobavu farhe. Va gu ki iv guzlan gegser avole mekohidin jop fuwetuge ijhebmob netopni mek ujani acief fuoto zel. Ulloc wij ibida wurus nun tesacul uhumud wed caf cofkipaw nator dab."
  },
  "apiKey": "e135b1d72fdd42cb3eb2d152ebbd6b307940d8576251486942d9f2f15432f973",
  "currency": {
    "code": "TND",
    "name": "Tunisia Dinar"
  }
}