{
  "name": "Ray Burton",
  "age": 48,
  "address": {
    "street": "Liaj Terrace",
    "city": "Mekenbuf",
    "state": "ME",
    "zip": "95951"
  },
  "contact": {
    "phone": "(539) 386-6419",
    "servicePhone": "800732134"
  },
  "birthday": "1988-10-04T03:52:31.583Z",
  "ip": "90.188.137.75",
  "foo": "bar",
  "profile": {
    "about": "Lufwegi uzube aluici nuzwozo siwi ewvef omojeudu surujisa tarotini ko uk hile. Sote ni upwov tuclek dab pigocupu ju liwiamu fufdububo acruf wafuhas zawkit nuzo. Socke zolegwo za ti ke dod jubi to joduv oz recif su etamem. Afohabzo sibtub ofeikomef igju ehebo mineci puzobna sivewe jupbubkoc docpov roviwehu pablowid no meg adonecta. Set dovu gufutuc zujife lomde lifavu ehuj feva izu ra cijeefu cabvojalo zoduk.",
    "bio": "Ekoolahi jun bih napuru ze zec upies avzohjul le jip biwejnuz ziroza vipatac jo deperlom. Uk va egnizol learil sejuspiz teggolo juhmawhin bif ag gemicfag ezi ezenuva muoj miar eppepviv esikuslat ijsumcos. Wesbusij sefot codagu pum kitom zeszo dimhof peivgec vefoka deof ru zuc meku op zawob rizud nezos. Vigfo jeugi pajejezi suk imefika gakliahi digos mace zov gihdazcuf fimal macusken beifje."
  },
  "apiKey": "2a43a41d1f328fe8e2a3eed150a9d21475fe5164d14637f93a199537f78d9f90",
  "currency": {
    "code": "HUF",
    "name": "Hungary Forint"
  }
}